simple_timer_plus/__init__.py
simple_timer_plus/timer.py
simple_timer_plus-0.0.1.dist-info/METADATA
simple_timer_plus-0.0.1.dist-info/WHEEL
simple_timer_plus-0.0.1.dist-info/top_level.txt
simple_timer_plus-0.0.1.dist-info/RECORD
