Metadata-Version: 2.1
Name: simple_timer_plus
Version: 0.0.1
Summary: A simple timer to measure task durations.
Home-page: https://github.com/orlandoabreugomes/simple-timer
Author: Orlando Gomes
Author-email: gomes.oa@gmail.com
Requires-Python: >=3.6
